iterweb/__init__.py
iterweb/exceptions.py
iterweb/pipeline.py
iterweb/reqresp.py
iterweb/spider.py
iterweb/utils/__init__.py
iterweb/utils/loadobject.py
iterweb/utils/reify.py
tests/__init__.py
tests/server.py
tests/test_parsing.py
tests/test_readme.py
tests/test_spider.py
iterweb-0.3.10.dist-info/LICENSE.md
iterweb-0.3.10.dist-info/METADATA
iterweb-0.3.10.dist-info/WHEEL
iterweb-0.3.10.dist-info/top_level.txt
iterweb-0.3.10.dist-info/RECORD
