Metadata-Version: 2.1
Name: iterweb
Version: 0.3.10
Summary: iterweb is a simple web scraper
Home-page: https://github.com/kneufeld/iterweb
Author: Kurt Neufeld
Author-email: kneufeld@burgundywall.com
License: MIT
Keywords: scraper
Platform: UNKNOWN
Classifier: Development Status :: 4 - Beta
Classifier: Intended Audience :: Developers
Classifier: License :: OSI Approved :: MIT License
Classifier: Natural Language :: English
Classifier: Operating System :: OS Independent
Classifier: Programming Language :: Python
Classifier: Programming Language :: Python :: 3.7
Classifier: Topic :: Database
Requires-Dist: aiohttp
Requires-Dist: parsel
Provides-Extra: dev
Requires-Dist: pytest ; extra == 'dev'
Requires-Dist: pytest-asyncio ; extra == 'dev'
Requires-Dist: pytest-aiohttp ; extra == 'dev'
Requires-Dist: nest-asyncio ; extra == 'dev'
